LICENSE
README.md
setup.py
webtool/__init__.py
webtool/application.py
webtool/schema.sql
webtool/static/favicon.ico
webtool/static/css/custom.css
webtool/static/css/pure-min.css
webtool/static/css/style.css
webtool/static/guide/XMind测试用例模板.xmind
webtool/static/guide/demo1_convert_result.png
webtool/static/guide/demo2_convert_result.png
webtool/static/guide/index.html
webtool/static/guide/index.md
webtool/static/guide/pypi_upload.png
webtool/static/guide/testcase_json_demo.png
webtool/static/guide/testcase_template_demo1.png
webtool/static/guide/testcase_template_demo2.png
webtool/static/guide/testcase_template_demo3.png
webtool/static/guide/testlink.png
webtool/static/guide/testlink_import_result.png
webtool/static/guide/testlink_select_file.png
webtool/static/guide/testlink_testcase_view.png
webtool/static/guide/testsuite_json_demo.png
webtool/static/guide/webtool.png
webtool/static/guide/webtool_cli.png
webtool/static/guide/xmind_testcase_demo.png
webtool/static/guide/xmind_testcase_template_rule.png
webtool/static/guide/xmind_testcase_template_rule1.png
webtool/static/guide/xmind_to_testcase_preview.png
webtool/static/guide/zentao_import_file.png
webtool/static/guide/zentao_import_result.png
webtool/static/guide/zentao_testcase_template.png
webtool/templates/index.html
webtool/templates/preview.html
xmind2testcase/TestRail.py
xmind2testcase/__about__.py
xmind2testcase/__init__.py
xmind2testcase/cli.py
xmind2testcase/const.py
xmind2testcase/gui.py
xmind2testcase/metadata.py
xmind2testcase/parser.py
xmind2testcase/testlink.py
xmind2testcase/utils.py
xmind2testcase/zentao.py
xmind2testcase_yys.egg-info/PKG-INFO
xmind2testcase_yys.egg-info/SOURCES.txt
xmind2testcase_yys.egg-info/dependency_links.txt
xmind2testcase_yys.egg-info/entry_points.txt
xmind2testcase_yys.egg-info/requires.txt
xmind2testcase_yys.egg-info/top_level.txt